<annotation>
	<folder>images</folder>
	<filename>127.jpeg</filename>
	<path>/home/anothername/Documents/Object-Detection-tf/images/127.jpeg</path>
	<source>
		<database>Unknown</database>
	</source>
	<size>
		<width>400</width>
		<height>300</height>
		<depth>3</depth>
	</size>
	<segmented>0</segmented>
	<object>
		<name>red</name>
		<pose>Unspecified</pose>
		<truncated>0</truncated>
		<difficult>0</difficult>
		<bndbox>
			<xmin>123</xmin>
			<ymin>135</ymin>
			<xmax>163</xmax>
			<ymax>178</ymax>
		</bndbox>
	</object>
	<object>
		<name>green</name>
		<pose>Unspecified</pose>
		<truncated>0</truncated>
		<difficult>0</difficult>
		<bndbox>
			<xmin>317</xmin>
			<ymin>122</ymin>
			<xmax>359</xmax>
			<ymax>162</ymax>
		</bndbox>
	</object>
</annotation>
